{
  "assets": {
    "5C542AD83DE164D4ABFA1AF12D246BCB": {
      "type": "texture",
      "index": 0,
      "url": { "native": "assets/18EE455E-6EC2-43A6-911B-3B4F35DEFCBE.pdf" },
      "width": 1920,
      "height": 1080
    },
    "CC90A4DF6F82D00A11DCEA91590453BC": {
      "type": "texture",
      "index": 1,
      "url": { "native": "assets/18EE455E-6EC2-43A6-911B-3B4F35DEFCBE.pdf" },
      "width": 1920,
      "height": 1080
    }
  },
  "events": [
    {
      "effects": [
        {
          "beginTime": 0,
          "baseLayer": {
            "animations": [],
            "initialState": {
              "affineTransform": [1, 0, 0, 1, 0, 0],
              "masksToBounds": false,
              "rotation": 0,
              "scale": 1,
              "position": { "pointX": 960, "pointY": 540 },
              "width": 1920,
              "sublayerTransform": [1, 0, 0, 0, 0, 1, 0, 0, 0, 0, 1, 0, 0, 0, 0, 1],
              "contentsRect": { "y": 0, "x": 0, "width": 1, "height": 1 },
              "opacity": 1,
              "edgeAntialiasingMask": 251658240,
              "height": 1080,
              "hidden": false,
              "anchorPoint": { "pointX": 0.5, "pointY": 0.5 }
            },
            "objectID": "0",
            "layers": [
              {
                "animations": [],
                "initialState": {
                  "affineTransform": [1, 0, 0, 1, 0, 0],
                  "masksToBounds": false,
                  "rotation": 0,
                  "scale": 1,
                  "position": { "pointX": 960, "pointY": 540 },
                  "width": 1920,
                  "sublayerTransform": [1, 0, 0, 0, 0, 1, 0, 0, 0, 0, 1, -0.00035007912466775983, 0, 0, 0, 1],
                  "contentsRect": { "y": 0, "x": 0, "width": 1, "height": 1 },
                  "opacity": 1,
                  "edgeAntialiasingMask": 251658240,
                  "height": 1080,
                  "hidden": false,
                  "anchorPoint": { "pointX": 0.5, "pointY": 0.5 }
                },
                "layers": [
                  {
                    "animations": [],
                    "layers": [],
                    "texturedRectangle": {
                      "isBackgroundTexture": false,
                      "singleTextureOpacity": 1,
                      "textureType": 0,
                      "textBaseline": 0,
                      "textXHeight": 0,
                      "isVerticalText": false
                    },
                    "initialState": {
                      "affineTransform": [1, 0, 0, 1, 0, 0],
                      "masksToBounds": false,
                      "rotation": 0,
                      "scale": 1,
                      "position": { "pointX": 960, "pointY": 540 },
                      "width": 1920,
                      "sublayerTransform": [1, 0, 0, 0, 0, 1, 0, 0, 0, 0, 1, 0, 0, 0, 0, 1],
                      "contentsRect": { "y": 0, "x": 0, "width": 1, "height": 1 },
                      "opacity": 1,
                      "edgeAntialiasingMask": 0,
                      "height": 1080,
                      "hidden": false,
                      "anchorPoint": { "pointX": 0.5, "pointY": 0.5 }
                    },
                    "texture": "CC90A4DF6F82D00A11DCEA91590453BC"
                  },
                  {
                    "animations": [
                      {
                        "additive": false,
                        "timeOffset": 0,
                        "beginTime": 0,
                        "from": { "scalar": false },
                        "repeatCount": 0,
                        "fillMode": "both",
                        "duration": 0.001,
                        "autoreverses": false,
                        "property": "hidden",
                        "to": { "scalar": true },
                        "removedOnCompletion": false
                      }
                    ],
                    "layers": [],
                    "texturedRectangle": {
                      "isBackgroundTexture": false,
                      "singleTextureOpacity": 1,
                      "textureType": 0,
                      "textBaseline": 0,
                      "textXHeight": 0,
                      "isVerticalText": false
                    },
                    "initialState": {
                      "affineTransform": [1, 0, 0, 1, 0, 0],
                      "masksToBounds": false,
                      "rotation": 0,
                      "scale": 1,
                      "position": { "pointX": 960, "pointY": 540 },
                      "width": 1920,
                      "sublayerTransform": [1, 0, 0, 0, 0, 1, 0, 0, 0, 0, 1, 0, 0, 0, 0, 1],
                      "contentsRect": { "y": 0, "x": 0, "width": 1, "height": 1 },
                      "opacity": 1,
                      "edgeAntialiasingMask": 0,
                      "height": 1080,
                      "hidden": false,
                      "anchorPoint": { "pointX": 0.5, "pointY": 0.5 }
                    },
                    "texture": "5C542AD83DE164D4ABFA1AF12D246BCB"
                  }
                ]
              }
            ]
          },
          "effects": [],
          "duration": 0.001,
          "type": "transition",
          "attributes": { "direction": 0 },
          "name": "none",
          "objectID": "0"
        }
      ],
      "automaticPlay": false,
      "hyperlinks": [],
      "accessibility": [
        {
          "text": "DESI VI. Cosmological constraints - Aug 2024 XII ICNFP @ Crete, Greece, 2024 ",
          "targetRectangle": { "y": 1041.0841376728204, "x": 1050.2376000976565, "width": 750.03999999999951, "height": 24.41986083984375 }
        },
        {
          "text": "13.5 million Bright Galaxies",
          "targetRectangle": { "y": 817.770751953125, "x": 204.0300938720703, "width": 401.37599999999998, "height": 38.07177734375 }
        },
        {
          "text": "(0.0 < z < 0.4)",
          "targetRectangle": { "y": 856.770751953125, "x": 306.35009387207032, "width": 196.73599999999999, "height": 38.07177734375 }
        },
        {
          "text": "Uendert Andrade (UMichigan)",
          "targetRectangle": { "y": 1042.0561835712579, "x": 8.4335163545608509, "width": 282.55999999999995, "height": 24.41986083984375 }
        },
        {
          "text": "16 million Emission Line Galaxies",
          "targetRectangle": { "y": 404.66970825195312, "x": 226.06174462890624, "width": 363.42400000000009, "height": 77.07177734375 }
        },
        {
          "text": "(0.6 < z < 1.6)",
          "targetRectangle": { "y": 482.66970825195312, "x": 304.95774462890626, "width": 196.73599999999999, "height": 38.07177734375 }
        },
        {
          "text": "From 2021-2026 DESI will measure precise redshifts to",
          "targetRectangle": { "y": 955.93626117706299, "x": 100.35192108154297, "width": 638.14400000000001, "height": 31.272003173828125 }
        },
        {
          "text": " ~40 million galaxies over 14,000 deg2 .",
          "targetRectangle": { "y": 987.93626117706299, "x": 100.35192108154297, "width": 460.6160000000001, "height": 31.272003173828125 }
        },
        {
          "text": "DESI Survey: Making the Largest 3D  Map of the Universe",
          "targetRectangle": { "y": 34.9344482421875, "x": 401.30154418945312, "width": 1470.4371013793211, "height": 67.372709655761724 }
        },
        {
          "text": "3 million",
          "targetRectangle": { "y": 211.17326354980469, "x": 341.96574462890624, "width": 122.72000000000003, "height": 38.07177734375 }
        },
        {
          "text": "Quasars (0.9 < z < 2.1)",
          "targetRectangle": { "y": 250.17326354980469, "x": 239.13374462890621, "width": 328.38400000000001, "height": 38.07177734375 }
        },
        {
          "text": "+ Ly-a forest (2.1 < z)",
          "targetRectangle": { "y": 289.17326354980469, "x": 248.33374462890626, "width": 309.98399999999992, "height": 38.07177734375 }
        },
        {
          "text": "￼",
          "targetRectangle": { "y": 1041.5740358829498, "x": 1872.6704055149457, "width": 22.240000000000009, "height": 23.44000244140625 }
        },
        {
          "text": "FB_IMG_1712288939650.jpg",
          "targetRectangle": { "y": 113.241455078125, "x": 949.00006103515625, "width": 881.97734069824219, "height": 907.00004196166992 }
        },
        {
          "text": "8 million Luminous Red Galaxies",
          "targetRectangle": { "y": 608.1998291015625, "x": 232.22209387207033, "width": 353.88800000000003, "height": 77.07177734375 }
        },
        {
          "text": "(0.4 < z < 1)",
          "targetRectangle": { "y": 686.1998291015625, "x": 319.69409387207031, "width": 170.048, "height": 38.07177734375 }
        },
        {
          "text": "Picture 8",
          "targetRectangle": { "y": 12.79906177520752, "x": 8.4552078247070312, "width": 339.9761962890625, "height": 149.27076721191406 }
        }
      ],
      "baseLayer": {
        "animations": [],
        "initialState": {
          "affineTransform": [1, 0, 0, 1, 0, 0],
          "masksToBounds": false,
          "rotation": 0,
          "scale": 1,
          "position": { "pointX": 960, "pointY": 540 },
          "width": 1920,
          "sublayerTransform": [1, 0, 0, 0, 0, 1, 0, 0, 0, 0, 1, 0, 0, 0, 0, 1],
          "contentsRect": { "y": 0, "x": 0, "width": 1, "height": 1 },
          "opacity": 1,
          "edgeAntialiasingMask": 251658240,
          "height": 1080,
          "hidden": false,
          "anchorPoint": { "pointX": 0.5, "pointY": 0.5 }
        },
        "objectID": "0",
        "layers": [
          {
            "animations": [],
            "initialState": {
              "affineTransform": [1, 0, 0, 1, 0, 0],
              "masksToBounds": false,
              "rotation": 0,
              "scale": 1,
              "position": { "pointX": 960, "pointY": 540 },
              "width": 1920,
              "sublayerTransform": [1, 0, 0, 0, 0, 1, 0, 0, 0, 0, 1, -0.00035007912466775983, 0, 0, 0, 1],
              "contentsRect": { "y": 0, "x": 0, "width": 1, "height": 1 },
              "opacity": 1,
              "edgeAntialiasingMask": 251658240,
              "height": 1080,
              "hidden": false,
              "anchorPoint": { "pointX": 0.5, "pointY": 0.5 }
            },
            "layers": [
              {
                "animations": [],
                "layers": [],
                "texturedRectangle": {
                  "isBackgroundTexture": false,
                  "singleTextureOpacity": 1,
                  "textureType": 0,
                  "textBaseline": 0,
                  "textXHeight": 0,
                  "isVerticalText": false
                },
                "initialState": {
                  "affineTransform": [1, 0, 0, 1, 0, 0],
                  "masksToBounds": false,
                  "rotation": 0,
                  "scale": 1,
                  "position": { "pointX": 960, "pointY": 540 },
                  "width": 1920,
                  "sublayerTransform": [1, 0, 0, 0, 0, 1, 0, 0, 0, 0, 1, 0, 0, 0, 0, 1],
                  "contentsRect": { "y": 0, "x": 0, "width": 1, "height": 1 },
                  "opacity": 1,
                  "edgeAntialiasingMask": 0,
                  "height": 1080,
                  "hidden": false,
                  "anchorPoint": { "pointX": 0.5, "pointY": 0.5 }
                },
                "texture": "5C542AD83DE164D4ABFA1AF12D246BCB"
              }
            ]
          }
        ]
      }
    }
  ]
}
